{
    "nodes":[
       {
          "name":[
             "x4"
          ],
          "datatype":"u64",
          "operation":"^",
          "arguments":[
             "arg1[0]",
             "0xfffffffffffffffe"
          ],
          "decisions":{
             "di_choose_arg":[
                1,
                [
                   "arg1[0]",
                   "0xfffffffffffffffe"
                ]
             ],
             "di_spill_location":[
                1,
                [
                   "c_mem",
                   "c_xmm_reg"
                ]
             ]
          },
          "decisionsHot":[
             
          ]
       },
       {
          "name":[
             "x3"
          ],
          "datatype":"u64",
          "operation":"-",
          "arguments":[
             "0x0",
             "arg1[0]"
          ],
          "decisions":{
             "di_choose_arg":[
                1,
                [
                   "0x0",
                   "arg1[0]"
                ]
             ],
             "di_spill_location":[
                1,
                [
                   "c_mem",
                   "c_xmm_reg"
                ]
             ]
          },
          "decisionsHot":[
             
          ]
       },
       {
          "name":[
             "x5"
          ],
          "datatype":"u64",
          "operation":"&",
          "arguments":[
             "x3",
             "x4"
          ],
          "decisions":{
             "di_choose_arg":[
                1,
                [
                   "x3",
                   "x4"
                ]
             ],
             "di_spill_location":[
                1,
                [
                   "c_mem",
                   "c_xmm_reg"
                ]
             ]
          },
          "decisionsHot":[
             
          ]
       },
       {
          "name":[
             "out1[0]"
          ],
          "datatype":"u64",
          "operation":"=",
          "arguments":[
             "x5"
          ],
          "decisions":{
             "di_choose_arg":[
                0,
                [
                   "x5"
                ]
             ],
             "di_spill_location":[
                0,
                [
                   "c_mem",
                   "c_xmm_reg"
                ]
             ]
          },
          "decisionsHot":[
             
          ]
       }
    ]
 }